collective.big.bang-1.1.0-py3.12-nspkg.pth
collective/big/bang/__init__.py
collective/big/bang/big.py
collective/big/bang/configure.zcml
collective/big/bang/event.py
collective/big/bang/expansion.py
collective/big/bang/interfaces.py
collective/big/bang/setuphandlers.py
collective/big/bang/testing.py
collective/big/bang/tests/__init__.py
collective/big/bang/tests/test_robot.py
collective/big/bang/tests/robot/test_example.robot
collective_big_bang-1.1.0.dist-info/licenses/LICENSE.GPL
collective_big_bang-1.1.0.dist-info/licenses/LICENSE.rst
collective_big_bang-1.1.0.dist-info/METADATA
collective_big_bang-1.1.0.dist-info/WHEEL
collective_big_bang-1.1.0.dist-info/namespace_packages.txt
collective_big_bang-1.1.0.dist-info/top_level.txt
collective_big_bang-1.1.0.dist-info/RECORD
